DataCleaner/__init__.py
DataCleaner/cleaner.py
datacleaner_ck-1.1.1.dist-info/METADATA
datacleaner_ck-1.1.1.dist-info/WHEEL
datacleaner_ck-1.1.1.dist-info/top_level.txt
datacleaner_ck-1.1.1.dist-info/RECORD
