Metadata-Version: 2.4
Name: datacleaner-ck
Version: 1.1.1
Summary: A practice project combining NumPy, Pandas, Matplotlib, and Seaborn for learning and revision.
Author-email: Ahmad Abdullah <ahmadleo498@gmail.com>
License-Expression: MIT
Project-URL: Homepage, https://github.com/ck-ahmad/DataCleaner
Project-URL: LinkedIn, https://www.linkedin.com/in/ahmad0763
Keywords: numpy,pandas,matplotlib,seaborn,machine-learning,data-science
Requires-Python: >=3.8
